eventsd/__init__.py
eventsd/events/__init__.py
eventsd/events/admin.py
eventsd/events/apps.py
eventsd/events/forms.py
eventsd/events/serializers.py
eventsd/events/tests.py
eventsd/events/urls.py
eventsd/events/migrations/0001_initial.py
eventsd/events/migrations/0002_initial.py
eventsd/events/migrations/__init__.py
eventsd/events/models/__init__.py
eventsd/events/models/events.py
eventsd/events/models/signup.py
eventsd/events/views/__init__.py
eventsd/events/views/events.py
eventsd/events/views/signup.py
eventsd/newsletter/__init__.py
eventsd/newsletter/admin.py
eventsd/newsletter/apps.py
eventsd/newsletter/models.py
eventsd/newsletter/tests.py
eventsd/newsletter/urls.py
eventsd/newsletter/views.py
eventsd/newsletter/migrations/0001_initial.py
eventsd/newsletter/migrations/0002_address_created_at.py
eventsd/newsletter/migrations/__init__.py
eventsd/sponsors/__init__.py
eventsd/sponsors/admin.py
eventsd/sponsors/apps.py
eventsd/sponsors/models.py
eventsd/sponsors/serializers.py
eventsd/sponsors/urls.py
eventsd/sponsors/views.py
eventsd/sponsors/migrations/0001_initial.py
eventsd/sponsors/migrations/0002_auto_20210922_1710.py
eventsd/sponsors/migrations/__init__.py
eventsd/users/__init__.py
eventsd/users/admin.py
eventsd/users/apps.py
eventsd/users/models.py
eventsd/users/serializers.py
eventsd/users/urls.py
eventsd/users/views.py
eventsd/users/migrations/0001_initial.py
eventsd/users/migrations/__init__.py
prologin_eventsd-0.1.4.dist-info/METADATA
prologin_eventsd-0.1.4.dist-info/WHEEL
prologin_eventsd-0.1.4.dist-info/top_level.txt
prologin_eventsd-0.1.4.dist-info/RECORD
